GraphDSL/__init__.py
GraphDSL/builder.py
GraphDSL/compiler.py
GraphDSL/exceptions.py
GraphDSL/factory.py
GraphDSL/graphAst.py
GraphDSL/test.py
GraphDSL/backend/abstract.py
GraphDSL/backend/igraph.py
GraphDSL/backend/networkx.py
GraphDSL-1.0.0.dist-info/LICENSE.txt
GraphDSL-1.0.0.dist-info/METADATA
GraphDSL-1.0.0.dist-info/WHEEL
GraphDSL-1.0.0.dist-info/top_level.txt
GraphDSL-1.0.0.dist-info/RECORD
