Metadata-Version: 2.1
Name: GraphDSL
Version: 1.0.0
Summary: A DSL for graph writing
Author-email: Maxmad68 <maxime@madrau.fr>
Project-URL: Homepage, https://github.com/Maxmad68/GraphDSL
Project-URL: Issues, https://github.com/Maxmad68/GraphDSL/issues
Classifier: Programming Language :: Python :: 3
Classifier: License :: OSI Approved :: MIT License
Classifier: Operating System :: OS Independent
Requires-Python: >=3.8
License-File: LICENSE.txt
